RCA_space/__init__.py
RCA_space/generate_rca_space.py
rca_space-0.0.1.dist-info/METADATA
rca_space-0.0.1.dist-info/WHEEL
rca_space-0.0.1.dist-info/licenses/LICENSE
rca_space-0.0.1.dist-info/RECORD
