Metadata-Version: 2.4
Name: RCA_space
Version: 0.0.1
Summary: The code responsible for generating the RCA spaces.
Project-URL: Homepage, https://github.com/grynova-ccc/Reference-based-Coordinate-Assignment
Author-email: Stiv Llenga <stivllenga@gmail.com>
License-File: LICENSE
Classifier: License :: OSI Approved :: MIT License
Classifier: Operating System :: OS Independent
Classifier: Programming Language :: Python :: 3
Requires-Python: >=3.7
